AUTHORS.rst
CONTRIBUTING.rst
HISTORY.rst
LICENSE
MANIFEST.in
README.rst
setup.cfg
setup.py
confgen/__init__.py
confgen/app.py
confgen.egg-info/PKG-INFO
confgen.egg-info/SOURCES.txt
confgen.egg-info/dependency_links.txt
confgen.egg-info/entry_points.txt
confgen.egg-info/not-zip-safe
confgen.egg-info/requires.txt
confgen.egg-info/top_level.txt
tests/__init__.py
tests/test_confgen.py