Metadata-Version: 1.1
Name: confgen
Version: 0.1.4
Summary: ConfGen is a little command utility that will     help you to generate some configurations thanks to jinja2 templating
Home-page: https://github.com/natjohan/confgen
Author: Natjohan
Author-email: contact@natjohan.info
License: BSD
Keywords: confgen
Platform: UNKNOWN
Classifier: Development Status :: 2 - Pre-Alpha
Classifier: Intended Audience :: Developers
Classifier: License :: OSI Approved :: BSD License
Classifier: Operating System :: OS Independent
Classifier: Natural Language :: English
Classifier: Programming Language :: Python :: 2.7
Classifier: Programming Language :: Python :: 3
Classifier: Programming Language :: Python :: 3.2
Classifier: Programming Language :: Python :: 3.3
Classifier: Environment :: Console
Classifier: Topic :: Utilities
